clash_controller/__init__.py
clash_controller/__main__.py
clash_controller/api.py
clash_controller/cli.py
clash_controller-0.0.1.dist-info/METADATA
clash_controller-0.0.1.dist-info/WHEEL
clash_controller-0.0.1.dist-info/entry_points.txt
clash_controller-0.0.1.dist-info/top_level.txt
clash_controller-0.0.1.dist-info/RECORD
