Metadata-Version: 2.4
Name: clash_controller
Version: 0.0.1
Summary: A controller for Clash
Author-email: Moha-Master <hongkongreporter@outlook.com>
License-Expression: MIT
Project-URL: Homepage, https://github.com/Moha-Master/Clash-Controller
Project-URL: Bug Tracker, https://github.com/Moha-Master/Clash-Controller/issues
Classifier: Programming Language :: Python :: 3
Classifier: Operating System :: OS Independent
Requires-Python: >=3.8
Requires-Dist: requests
Requires-Dist: requests_unixsocket
Requires-Dist: InquirerPy
